antlr4_vba/__init__.py
antlr4_vba/py.typed
antlr4_vba/vbaLexer.py
antlr4_vba/vbaParser.py
antlr4_vba/vbaParserListener.py
antlr4_vba/vbaParserVisitor.py
antlr4_vba/vba_ccLexer.py
antlr4_vba/vba_ccListener.py
antlr4_vba/vba_ccParser.py
antlr4_vba/vba_ccVisitor.py
antlr4_vba/vba_likeLexer.py
antlr4_vba/vba_likeListener.py
antlr4_vba/vba_likeParser.py
antlr4_vba/vba_likeVisitor.py
antlr4_vba/antlr4_vba/__init__.pyi
antlr4_vba/antlr4_vba/vbaLexer.pyi
antlr4_vba/antlr4_vba/vbaParser.pyi
antlr4_vba/antlr4_vba/vbaParserListener.pyi
antlr4_vba/antlr4_vba/vbaParserVisitor.pyi
antlr4_vba/antlr4_vba/vba_ccLexer.pyi
antlr4_vba/antlr4_vba/vba_ccListener.pyi
antlr4_vba/antlr4_vba/vba_ccParser.pyi
antlr4_vba/antlr4_vba/vba_ccVisitor.pyi
antlr4_vba/antlr4_vba/vba_likeLexer.pyi
antlr4_vba/antlr4_vba/vba_likeListener.pyi
antlr4_vba/antlr4_vba/vba_likeParser.pyi
antlr4_vba/antlr4_vba/vba_likeVisitor.pyi
antlr4_vba-0.0.62.dist-info/LICENSE
antlr4_vba-0.0.62.dist-info/METADATA
antlr4_vba-0.0.62.dist-info/WHEEL
antlr4_vba-0.0.62.dist-info/top_level.txt
antlr4_vba-0.0.62.dist-info/RECORD
