Metadata-Version: 2.1
Name: antlr4_vba
Version: 0.0.62
Summary: VBA targeted antlr4 parsing classes.
Author-email: Kevin Nowaczyk <beakerboy99@yahoo.com>
Project-URL: Homepage, https://github.com/Beakerboy/antlr4-vba/
Project-URL: Bug Tracker, https://github.com/Beakerboy/antlr4-vba/issues
Classifier: Programming Language :: Python :: 3
Classifier: License :: OSI Approved :: MIT License
Classifier: Operating System :: OS Independent
Requires-Python: >=3.7
License-File: LICENSE
Requires-Dist: antlr4-python3-runtime
Requires-Dist: antlr4-tools
Provides-Extra: tests
Requires-Dist: mypy ; extra == 'tests'
